LICENSE
README.rst
setup.py
fastapi_addto/__init__.py
fastapi_addto/__version__.py
fastapi_addto.egg-info/PKG-INFO
fastapi_addto.egg-info/SOURCES.txt
fastapi_addto.egg-info/dependency_links.txt
fastapi_addto.egg-info/requires.txt
fastapi_addto.egg-info/top_level.txt
fastapi_addto/adapter/__init__.py
fastapi_addto/adapter/message/__init__.py
fastapi_addto/adapter/message/kafka.py
fastapi_addto/adapter/message/rabbitmq.py
fastapi_addto/adapter/message/redis.py
fastapi_addto/framework/__init__.py
fastapi_addto/framework/base_model.py
fastapi_addto/framework/base_repository.py
fastapi_addto/framework/base_schema.py
fastapi_addto/framework/custom_exception.py
fastapi_addto/framework/database.py
fastapi_addto/framework/dependencies.py
fastapi_addto/framework/exception.py
fastapi_addto/framework/logger.py
fastapi_addto/framework/response_model.py
fastapi_addto/framework/security.py